h5torch/__init__.py
h5torch/dataset.py
h5torch/file.py
h5torch-0.3.1.dist-info/licenses/LICENSE
h5torch-0.3.1.dist-info/METADATA
h5torch-0.3.1.dist-info/WHEEL
h5torch-0.3.1.dist-info/top_level.txt
h5torch-0.3.1.dist-info/RECORD
