Metadata-Version: 2.4
Name: h5torch
Version: 0.3.1
Summary: HDF5 data utilities for PyTorch
Home-page: https://github.com/gdewael/h5torch
Author: Gaetan De Waele
Requires-Python: >=3.9
License-File: LICENSE
Requires-Dist: numpy
Requires-Dist: h5py
Requires-Dist: torch
Requires-Dist: scipy
Dynamic: license-file
